principia/__init__.py
principia/principia.py
principia/utils.py
principia-0.1.2.dist-info/licenses/LICENSE
principia-0.1.2.dist-info/METADATA
principia-0.1.2.dist-info/WHEEL
principia-0.1.2.dist-info/top_level.txt
principia-0.1.2.dist-info/RECORD
