Metadata-Version: 2.4
Name: principia
Version: 0.1.2
Summary: A lightweight, powerful Python framework for building self-verifying, robust, and elegant software by making all implicit assumptions explicit and verifiable at runtime.
Author-email: Keenan Finkelstein <keenanfinkelstein@gmail.com>
Project-URL: Homepage, https://github.com/krflol/principia
Classifier: Programming Language :: Python :: 3
Classifier: License :: OSI Approved :: MIT License
Classifier: Operating System :: OS Independent
Requires-Python: >=3.8
License-File: LICENSE
Requires-Dist: pandas
Requires-Dist: statsmodels
Requires-Dist: requests
Dynamic: license-file
